LICENSE
MANIFEST.in
README.md
requirements.txt
setup.cfg
setup.py
unsplash/__init__.py
unsplash/api.py
unsplash/auth.py
unsplash/client.py
unsplash/collection.py
unsplash/errors.py
unsplash/models.py
unsplash/photo.py
unsplash/search.py
unsplash/stat.py
unsplash/user.py
unsplash.egg-info/PKG-INFO
unsplash.egg-info/SOURCES.txt
unsplash.egg-info/dependency_links.txt
unsplash.egg-info/requires.txt
unsplash.egg-info/top_level.txt
unsplash.egg-info/zip-safe